Metadata-Version: 2.1
Name: OSLogManagement
Version: 0.0.1
Summary: Output of OS commands to str-convertible list for assignment to variables.
Home-page: https://github.com/TITIR1X/PyLogManagement
Author: Santiago Benavidez (TITIR1X)
Author-email: SantiagoBenavidez@pythondeveloper.com
License: MIT
Keywords: Python,Console,Log,Management,RegEx,Variable,String,Output of OS commands to str-convertible list for assignment to variables.
Classifier: Development Status :: 3 - Alpha
Classifier: Intended Audience :: Developers
Classifier: Topic :: Software Development :: Build Tools
Classifier: License :: OSI Approved :: MIT License
Classifier: Programming Language :: Python :: 3
License-File: LICENSE
